clickhouse_django_logger/ __init__.py
clickhouse_django_logger/apps.py
clickhouse_django_logger/config.py
clickhouse_django_logger/handlers.py
clickhouse_django_logger/tasks.py
clickhouse_django_logger/utils.py
clickhouse_django_logger-0.1.5.dist-info/METADATA
clickhouse_django_logger-0.1.5.dist-info/WHEEL
clickhouse_django_logger-0.1.5.dist-info/top_level.txt
clickhouse_django_logger-0.1.5.dist-info/RECORD
