Metadata-Version: 2.1
Name: clickhouse-django-logger
Version: 0.1.5
Summary: Логгер Django для ClickHouse с интеграцией Celery.
Author-email: Алексей <vipzenit666666@gmail.com>
License: MIT
Project-URL: Homepage, https://github.com/single-service/clickhouse_django_logger
Project-URL: Issues, https://github.com/single-service/clickhouse_django_logger/issues
Classifier: Framework :: Django
Classifier: Intended Audience :: Developers
Classifier: License :: OSI Approved :: MIT License
Classifier: Programming Language :: Python :: 3
Classifier: Programming Language :: Python :: 3 :: Only
Classifier: Programming Language :: Python :: 3.6
Classifier: Programming Language :: Python :: 3.7
Classifier: Programming Language :: Python :: 3.8
Classifier: Programming Language :: Python :: 3.9
Classifier: Topic :: Software Development :: Libraries :: Python Modules
Requires-Python: >=3.6
Requires-Dist: Django >=2.2
Requires-Dist: celery >=5.0
Requires-Dist: requests >=2.0
Provides-Extra: dev
Requires-Dist: pytest ; extra == 'dev'
Requires-Dist: mypy ; extra == 'dev'
Requires-Dist: flake8 ; extra == 'dev'
Provides-Extra: docs
Requires-Dist: sphinx ; extra == 'docs'
